multikeyjwt/__init__.py
multikeyjwt/config.py
multikeyjwt/console.py
multikeyjwt/jwt/__init__.py
multikeyjwt/jwt/common.py
multikeyjwt/jwt/issuer.py
multikeyjwt/jwt/verifier.py
multikeyjwt/keygen.py
multikeyjwt/middleware/__init__.py
multikeyjwt/middleware/jwtbearer.py
multikeyjwt/py.typed
multikeyjwt-1.4.3.dist-info/LICENSE
multikeyjwt-1.4.3.dist-info/METADATA
multikeyjwt-1.4.3.dist-info/WHEEL
multikeyjwt-1.4.3.dist-info/entry_points.txt
multikeyjwt-1.4.3.dist-info/RECORD
