Metadata-Version: 2.3
Name: multikeyjwt
Version: 1.4.3
Summary: Verify JWTs with multiple public keys, FastAPI middleware for auth
License: MIT
Author: Eero af Heurlin
Author-email: eero.afheurlin@iki.fi
Requires-Python: >=3.9,<4.0
Classifier: License :: OSI Approved :: MIT License
Classifier: Programming Language :: Python :: 3
Classifier: Programming Language :: Python :: 3.9
Classifier: Programming Language :: Python :: 3.10
Classifier: Programming Language :: Python :: 3.11
Classifier: Programming Language :: Python :: 3.12
Classifier: Programming Language :: Python :: 3.13
Provides-Extra: all
Provides-Extra: fastapi
Requires-Dist: click (>=8.0,<9.0)
Requires-Dist: cryptography (>=41.0)
Requires-Dist: fastapi (>0.89,<1.0) ; extra == "fastapi" or extra == "all"
Requires-Dist: libadvian (>=1.0,<2.0)
Requires-Dist: pendulum (>=3.0,<4.0)
Requires-Dist: pyjwt[crypto] (>=2.6,<3.0)
Project-URL: Homepage, https://github.com/pvarki/python-multikeyjwt/
Project-URL: Repository, https://github.com/pvarki/python-multikeyjwt/
